stpstone/__init__.py
stpstone/_config/countries/br/bylaws/investment_funds.yaml
stpstone/_config/countries/br/exchange/anbima_550_listing.yaml
stpstone/_config/countries/br/exchange/anbima_site_infos.yaml
stpstone/_config/countries/br/exchange/bmf_interest_rates.yaml
stpstone/_config/countries/br/exchange/bvmf_bov.yaml
stpstone/_config/countries/br/exchange/consolidated_trades.yaml
stpstone/_config/countries/br/exchange/consolidated_trades_after_mkt.yaml
stpstone/_config/countries/br/exchange/futures_closing_adj.yaml
stpstone/_config/countries/br/exchange/historical_sigma.yaml
stpstone/_config/countries/br/exchange/indexes_anbima.yaml
stpstone/_config/countries/br/exchange/indexes_anbima_data.yaml
stpstone/_config/countries/br/exchange/indexes_theor_portf.yaml
stpstone/_config/countries/br/exchange/options_calendar.yaml
stpstone/_config/countries/br/exchange/search_by_trading_session.yaml
stpstone/_config/countries/br/exchange/trading_hours.yaml
stpstone/_config/countries/br/exchange/up2data_registries.yaml
stpstone/_config/countries/br/exchange/up2data_volumes_trd.yaml
stpstone/_config/countries/br/exchange/warranty.yaml
stpstone/_config/countries/br/macroeconomics/anbima_pmi_forecasts.yaml
stpstone/_config/countries/br/macroeconomics/b3_financial_indicators.yaml
stpstone/_config/countries/br/macroeconomics/investingcom_br.yaml
stpstone/_config/countries/br/macroeconomics/olinda_bcb.yaml
stpstone/_config/countries/br/macroeconomics/ptax_bcb.yaml
stpstone/_config/countries/br/macroeconomics/sgs_bcb.yaml
stpstone/_config/countries/br/macroeconomics/sidra_ibge.yaml
stpstone/_config/countries/br/macroeconomics/yahii_others.yaml
stpstone/_config/countries/br/macroeconomics/yahii_rates.yaml
stpstone/_config/countries/br/otc/debentures.yaml
stpstone/_config/countries/br/registries/anbima_data_api.yaml
stpstone/_config/countries/br/registries/anbima_data_debentures.yaml
stpstone/_config/countries/br/registries/anbima_data_funds.yaml
stpstone-2.0.29.dist-info/LICENSE
stpstone-2.0.29.dist-info/METADATA
stpstone-2.0.29.dist-info/WHEEL
stpstone-2.0.29.dist-info/RECORD
