Metadata-Version: 2.3
Name: stpstone
Version: 2.0.29
Summary: Solid financial ETL, analytics and utils with support to global markets.
License: MIT
Keywords: stpstone,python,financial,data,utils,analytics,ingestion,b3,cvm,exchange,derivatives,quantitative,risk,portfolio,fixed income,options,futures,market data,macroeconomic,scraping,statistics,time series,cryptocurrency,brazilian markets,pricing models,financial mathematics
Author: guilhermegor
Author-email: github.bucked794@silomails.com
Requires-Python: >=3.9,<3.14
Classifier: Development Status :: 5 - Production/Stable
Classifier: Intended Audience :: Developers
Classifier: Intended Audience :: Financial and Insurance Industry
Classifier: Intended Audience :: Science/Research
Classifier: License :: OSI Approved :: MIT License
Classifier: Operating System :: OS Independent
Classifier: Programming Language :: Python :: 3
Classifier: Programming Language :: Python :: 3.9
Classifier: Programming Language :: Python :: 3.10
Classifier: Programming Language :: Python :: 3.11
Classifier: Programming Language :: Python :: 3.12
Classifier: Programming Language :: Python :: 3.13
Classifier: Topic :: Office/Business :: Financial
Classifier: Topic :: Office/Business :: Financial :: Spreadsheet
Classifier: Topic :: Office/Business :: Office Suites
Classifier: Topic :: Office/Business :: Scheduling
Classifier: Topic :: Other/Nonlisted Topic
Classifier: Topic :: Scientific/Engineering :: Mathematics
Requires-Dist: backoff (>=2.2.1)
Requires-Dist: basicauth (>=1.0.0)
Requires-Dist: bcrypt (>=4.3.0)
Requires-Dist: beautifulsoup4 (>=4.12.0)
Requires-Dist: boto (>=2.49.0)
Requires-Dist: businesstimedelta (>=1.0.1)
Requires-Dist: chardet (>=5.2.0)
Requires-Dist: countryinfo (>=0.1.2)
Requires-Dist: cvxopt (>=1.3.2)
Requires-Dist: ftfy (>=6.3.1)
Requires-Dist: joblib (>=1.4.2)
Requires-Dist: keyring (>=25.6.0)
Requires-Dist: lxml (>=5.3.0)
Requires-Dist: minio (>=7.2.15)
Requires-Dist: mlxtend (>=0.23.1)
Requires-Dist: more-itertools (>=10.6.0)
Requires-Dist: mystic (>=0.4.4)
Requires-Dist: nelson-siegel-svensson (>=0.5.0)
Requires-Dist: numpy (==1.24.4) ; python_version == "3.9"
Requires-Dist: numpy (>=2.0.0) ; python_version >= "3.10"
Requires-Dist: numpy-financial (>=1.0.0)
Requires-Dist: openai (>=1.79.0)
Requires-Dist: openpyxl (>=3.1.0)
Requires-Dist: pandas (>=2.1.0)
Requires-Dist: pdfplumber (>=0.11.5)
Requires-Dist: playwright (>=1.52.0)
Requires-Dist: plotly (>=6.0.0)
Requires-Dist: psutil (>=7.0.0)
Requires-Dist: psycopg (>=3.2.4)
Requires-Dist: py7zr (>=0.22.0)
Requires-Dist: pycountry (>=24.6.1)
Requires-Dist: pycountry-convert (>=0.7.2)
Requires-Dist: pycurl (>=7.45.2)
Requires-Dist: pydantic (>=2.11.5)
Requires-Dist: pymsteams (>=0.2.5)
Requires-Dist: pymupdf[fitz] (>=1.23.0)
Requires-Dist: pymysql (>=1.1.1)
Requires-Dist: pyodbc (>=5.1.0)
Requires-Dist: pypdf (>=4.0.0)
Requires-Dist: python-dateutil (>=2.8.2)
Requires-Dist: pywin32 (>=308) ; sys_platform == "win32"
Requires-Dist: pyyaml (>=6.0.2)
Requires-Dist: requests (>=2.31.0)
Requires-Dist: scikit-learn (>=1.4.0)
Requires-Dist: scipy (>=1.11.0,!=1.16.0)
Requires-Dist: seaborn (>=0.13.2)
Requires-Dist: selenium (>=4.30.0)
Requires-Dist: sendgrid (>=6.11.0)
Requires-Dist: slack (>=0.0.2)
Requires-Dist: sqlalchemy (>=1.4.36)
Requires-Dist: statsmodels (>=0.14.4)
Requires-Dist: sympy (>=1.13.3)
Requires-Dist: tabula-py (==2.9.0) ; python_version == "3.9"
Requires-Dist: tabula-py (>=2.10.0) ; python_version >= "3.10"
Requires-Dist: unidecode (>=1.3.8)
Requires-Dist: urllib3 (>=2.0.0)
Requires-Dist: validate-docbr (>=1.10.0)
Requires-Dist: webdriver-manager (>=4.0.2)
Requires-Dist: wget (>=3.2)
Requires-Dist: wmi (==1.5.1) ; sys_platform == "win32"
Requires-Dist: workalendar (>=17.0.0)
Requires-Dist: xlrd (>=2.0.1)
Requires-Dist: xlwt (>=1.3.0)
Requires-Dist: yfinance (>=0.2.52)
Project-URL: Bug Reports, https://github.com/guilhermegor/stpstone/issues
Project-URL: Homepage, https://github.com/guilhermegor/stpstone
Project-URL: Repository, https://github.com/guilhermegor/stpstone
Project-URL: Source, https://github.com/guilhermegor/stpstone
